Workbook
Name Slicer_STATUS: #N/A

Sheet Auto Sales data
A1: ORDERNUMBER | B1: ORDER QUANTITY | C1: PRICE EACH | D1: ORDERLINE NUMBER | E1: SALES | F1: ORDERDATE | G1: MONTH | H1: DAYS_SINCE_LASTORDER | I1: STATUS | J1: PRODUCTLINE | K1: MSRP | L1: PRODUCTCODE | M1: Column1 | N1: PHONE NUMBER | O1: ADDRESSLINE1 | P1: CITY | Q1: POSTAL CODE | R1: COUNTRY | S1: FULL NAME | T1: DEALSIZE | U1: PROFIT | V1: % PROFIT
A2: 10107 | B2: 30 | C2: 95.7 | D2: 2 | E2: 2871 | F2: 43155 | G2: February | H2: 28months | I2: Shipped | J2: Motorcycles | K2: 95 | L2: S10_1678 | N2: 2125557818 | O2: 897 Long Airport Avenue | P2: NYC | Q2: 10022 | R2: USA | S2: Yu Kwai | T2: Small | U2: =Auto[[#This Row],[SALES]]-(Auto[[#This Row],[MSRP]]*Auto[[#This Row],[ORDER QUANTITY]]) -> 21 | V2: =Auto[[#This Row],[PROFIT]]/100 -> 0.21
A3: 10121 | B3: 34 | C3: 81.35 | D3: 5 | E3: 2765.9 | F3: 43227 | G3: May | H3: 25months | I3: Shipped | J3: Motorcycles | K3: 95 | L3: S10_1678 | N3: 26.47.1555 | O3: 59 rue de l'Abbaye | P3: Reims | Q3: 51100 | R3: France | S3: Henriot Paul | T3: Small | U3: =Auto[[#This Row],[SALES]]-(Auto[[#This Row],[MSRP]]*Auto[[#This Row],[ORDER QUANTITY]]) -> -464.1 | V3: =Auto[[#This Row],[PROFIT]]/100 -> -4.641
A4: 10134 | B4: 41 | C4: 94.74 | D4: 2 | E4: 3884.34 | F4: 43282 | G4: July | H4: 23months | I4: Shipped | J4: Motorcycles | K4: 95 | L4: S10_1678 | N4: +33 1 46 62 7555 | O4: 27 rue du Colonel Pierre Avia | P4: Paris | Q4: 75508 | R4: France | S4: Da Cunha Daniel | T4: Medium | U4: =Auto[[#This Row],[SALES]]-(Auto[[#This Row],[MSRP]]*Auto[[#This Row],[ORDER QUANTITY]]) -> -10.66 | V4: =Auto[[#This Row],[PROFIT]]/100 -> -0.1066
A5: 10145 | B5: 45 | C5: 83.26 | D5: 6 | E5: 3746.7 | F5: 43337 | G5: August | H5: 22months | I5: Shipped | J5: Motorcycles | K5: 95 | L5: S10_1678 | N5: 6265557265 | O5: 78934 Hillside Dr. | P5: Pasadena | Q5: 90003 | R5: USA | S5: Young Julie | T5: Medium | U5: =Auto[[#This Row],[SALES]]-(Auto[[#This Row],[MSRP]]*Auto[[#This Row],[ORDER QUANTITY]]) -> -528.3 | V5: =Auto[[#This Row],[PROFIT]]/100 -> -5.283
A6: 10168 | B6: 36 | C6: 96.66 | D6: 1 | E6: 3479.76 | F6: 43401 | G6: October | H6: 20months | I6: Shipped | J6: Motorcycles | K6: 95 | L6: S10_1678 | N6: 6505556809 | O6: 9408 Furth Circle | P6: Burlingame | Q6: 94217 | R6: USA | S6: Hirano Juri | T6: Medium | U6: =Auto[[#This Row],[SALES]]-(Auto[[#This Row],[MSRP]]*Auto[[#This Row],[ORDER QUANTITY]]) -> 59.76 | V6: =Auto[[#This Row],[PROFIT]]/100 -> 0.5976
A7: 10180 | B7: 29 | C7: 86.13 | D7: 9 | E7: 2497.77 | F7: 43415 | G7: November | H7: 19months | I7: Shipped | J7: Motorcycles | K7: 95 | L7: S10_1678 | N7: 20.16.1555 | O7: 184, chausse de Tournai | P7: Lille | Q7: 59000 | R7: France | S7: Rance Martine | T7: Small | U7: =Auto[[#This Row],[SALES]]-(Auto[[#This Row],[MSRP]]*Auto[[#This Row],[ORDER QUANTITY]]) -> -257.23 | V7: =Auto[[#This Row],[PROFIT]]/100 -> -2.5723
A8: 10188 | B8: 48 | C8: 114.84 | D8: 1 | E8: 5512.32 | F8: 43422 | G8: November | H8: 19months | I8: Shipped | J8: Motorcycles | K8: 95 | L8: S10_1678 | N8: +47 2267 3215 | O8: Drammen 121, PR 744 Sentrum | P8: Bergen | Q8: N 5804 | R8: Norway | S8: Oeztan Veysel | T8: Medium | U8: =Auto[[#This Row],[SALES]]-(Auto[[#This Row],[MSRP]]*Auto[[#This Row],[ORDER QUANTITY]]) -> 952.32 | V8: =Auto[[#This Row],[PROFIT]]/100 -> 9.5232
A9: 10211 | B9: 41 | C9: 114.84 | D9: 14 | E9: 4708.44 | F9: 43480 | G9: January | H9: 17months | I9: Shipped | J9: Motorcycles | K9: 95 | L9: S10_1678 | N9: (1) 47.55.6555 | O9: 25, rue Lauriston | P9: Paris | Q9: 75016 | R9: France | S9: Perrier Dominique | T9: Medium | U9: =Auto[[#This Row],[SALES]]-(Auto[[#This Row],[MSRP]]*Auto[[#This Row],[ORDER QUANTITY]]) -> 813.44 | V9: =Auto[[#This Row],[PROFIT]]/100 -> 8.1344
A10: 10223 | B10: 37 | C10: 107.18 | D10: 1 | E10: 3965.66 | F10: 43516 | G10: February | H10: 16months | I10: Shipped | J10: Motorcycles | K10: 95 | L10: S10_1678 | N10: 03 9520 4555 | O10: 636 St Kilda Road | P10: Melbourne | Q10: 3004 | R10: Australia | S10: Ferguson Peter | T10: Medium | U10: =Auto[[#This Row],[SALES]]-(Auto[[#This Row],[MSRP]]*Auto[[#This Row],[ORDER QUANTITY]]) -> 450.66 | V10: =Auto[[#This Row],[PROFIT]]/100 -> 4.5066
A11: 10237 | B11: 23 | C11: 101.44 | D11: 7 | E11: 2333.12 | F11: 43560 | G11: April | H11: 14months | I11: Shipped | J11: Motorcycles | K11: 95 | L11: S10_1678 | N11: 2125551500 | O11: 2678 Kingston Rd. | P11: NYC | Q11: 10022 | R11: USA | S11: Frick Michael | T11: Small | U11: =Auto[[#This Row],[SALES]]-(Auto[[#This Row],[MSRP]]*Auto[[#This Row],[ORDER QUANTITY]]) -> 148.12 | V11: =Auto[[#This Row],[PROFIT]]/100 -> 1.4812
A12: 10251 | B12: 28 | C12: 113.88 | D12: 2 | E12: 3188.64 | F12: 43603 | G12: May | H12: 13months | I12: Shipped | J12: Motorcycles | K12: 95 | L12: S10_1678 | N12: 2015559350 | O12: 7476 Moss Rd. | P12: Newark | Q12: 94019 | R12: USA | S12: Brown William | T12: Medium | U12: =Auto[[#This Row],[SALES]]-(Auto[[#This Row],[MSRP]]*Auto[[#This Row],[ORDER QUANTITY]]) -> 528.64 | V12: =Auto[[#This Row],[PROFIT]]/100 -> 5.2864
A13: 10263 | B13: 34 | C13: 108.14 | D13: 2 | E13: 3676.76 | F13: 43644 | G13: June | H13: 12months | I13: Shipped | J13: Motorcycles | K13: 95 | L13: S10_1678 | N13: 2035552570 | O13: 25593 South Bay Ln. | P13: Bridgewater | Q13: 97562 | R13: USA | S13: King Julie | T13: Medium | U13: =Auto[[#This Row],[SALES]]-(Auto[[#This Row],[MSRP]]*Auto[[#This Row],[ORDER QUANTITY]]) -> 446.76 | V13: =Auto[[#This Row],[PROFIT]]/100 -> 4.4676
A14: 10275 | B14: 45 | C14: 92.83 | D14: 1 | E14: 4177.35 | F14: 43669 | G14: July | H14: 11months | I14: Shipped | J14: Motorcycles | K14: 95 | L14: S10_1678 | N14: 40.67.8555 | O14: 67, rue des Cinquante Otages | P14: Nantes | Q14: 44000 | R14: France | S14: Labrune Janine | T14: Medium | U14: =Auto[[#This Row],[SALES]]-(Auto[[#This Row],[MSRP]]*Auto[[#This Row],[ORDER QUANTITY]]) -> -97.65 | V14: =Auto[[#This Row],[PROFIT]]/100 -> -0.9765
A15: 10285 | B15: 36 | C15: 113.88 | D15: 6 | E15: 4099.68 | F15: 43704 | G15: August | H15: 10months | I15: Shipped | J15: Motorcycles | K15: 95 | L15: S10_1678 | N15: 6175558555 | O15: 39323 Spinnaker Dr. | P15: Cambridge | Q15: 51247 | R15: USA | S15: Hernandez Marta | T15: Medium | U15: =Auto[[#This Row],[SALES]]-(Auto[[#This Row],[MSRP]]*Auto[[#This Row],[ORDER QUANTITY]]) -> 679.68 | V15: =Auto[[#This Row],[PROFIT]]/100 -> 6.7968
A16: 10299 | B16: 23 | C16: 112.93 | D16: 9 | E16: 2597.39 | F16: 43738 | G16: September | H16: 9months | I16: Shipped | J16: Motorcycles | K16: 95 | L16: S10_1678 | N16: 90-224 8555 | O16: Keskuskatu 45 | P16: Helsinki | Q16: 21240 | R16: Finland | S16: Karttunen Matti | T16: Small | U16: =Auto[[#This Row],[SALES]]-(Auto[[#This Row],[MSRP]]*Auto[[#This Row],[ORDER QUANTITY]]) -> 412.39 | V16: =Auto[[#This Row],[PROFIT]]/100 -> 4.1239
A17: 10309 | B17: 41 | C17: 107.18 | D17: 5 | E17: 4394.38 | F17: 43753 | G17: October | H17: 8months | I17: Shipped | J17: Motorcycles | K17: 95 | L17: S10_1678 | N17: 07-98 9555 | O17: Erling Skakkes gate 78 | P17: Stavern | Q17: 4110 | R17: Norway | S17: Bergulfsen Jonas | T17: Medium | U17: =Auto[[#This Row],[SALES]]-(Auto[[#This Row],[MSRP]]*Auto[[#This Row],[ORDER QUANTITY]]) -> 499.38 | V17: =Auto[[#This Row],[PROFIT]]/100 -> 4.9938
A18: 10318 | B18: 46 | C18: 94.74 | D18: 1 | E18: 4358.04 | F18: 43771 | G18: November | H18: 8months | I18: Shipped | J18: Motorcycles | K18: 95 | L18: S10_1678 | N18: 2155551555 | O18: 7586 Pompton St. | P18: Allentown | Q18: 70267 | R18: USA | S18: Yu Kyung | T18: Medium | U18: =Auto[[#This Row],[SALES]]-(Auto[[#This Row],[MSRP]]*Auto[[#This Row],[ORDER QUANTITY]]) -> -11.96 | V18: =Auto[[#This Row],[PROFIT]]/100 -> -0.1196
A19: 10329 | B19: 42 | C19: 104.67 | D19: 1 | E19: 4396.14 | F19: 43784 | G19: November | H19: 7months | I19: Shipped | J19: Motorcycles | K19: 95 | L19: S10_1678 | N19: 2125557818 | O19: 897 Long Airport Avenue | P19: NYC | Q19: 10022 | R19: USA | S19: Yu Kwai | T19: Medium | U19: =Auto[[#This Row],[SALES]]-(Auto[[#This Row],[MSRP]]*Auto[[#This Row],[ORDER QUANTITY]]) -> 406.14 | V19: =Auto[[#This Row],[PROFIT]]/100 -> 4.0614
A20: 10341 | B20: 41 | C20: 188.73 | D20: 9 | E20: 7737.93 | F20: 43793 | G20: November | H20: 7months | I20: Shipped | J20: Motorcycles | K20: 95 | L20: S10_1678 | N20: 6562-9555 | O20: Geislweg 14 | P20: Salzburg | Q20: 5020 | R20: Austria | S20: Pipps Georg | T20: Large | U20: =Auto[[#This Row],[SALES]]-(Auto[[#This Row],[MSRP]]*Auto[[#This Row],[ORDER QUANTITY]]) -> 3842.93 | V20: =Auto[[#This Row],[PROFIT]]/100 -> 38.4293
A21: 10361 | B21: 20 | C21: 72.55 | D21: 13 | E21: 1451 | F21: 43816 | G21: December | H21: 6months | I21: Shipped | J21: Motorcycles | K21: 95 | L21: S10_1678 | N21: +61 2 9495 8555 | O21: Monitor Money Building, 815 Pacific Hwy | P21: Chatswood | Q21: 2067 | R21: Australia | S21: Huxley Adrian | T21: Small | U21: =Auto[[#This Row],[SALES]]-(Auto[[#This Row],[MSRP]]*Auto[[#This Row],[ORDER QUANTITY]]) -> -449 | V21: =Auto[[#This Row],[PROFIT]]/100 -> -4.49
A22: 10375 | B22: 21 | C22: 34.91 | D22: 12 | E22: 733.11 | F22: 43864 | G22: February | H22: 5months | I22: Shipped | J22: Motorcycles | K22: 95 | L22: S10_1678 | N22: 40.67.8555 | O22: 67, rue des Cinquante Otages | P22: Nantes | Q22: 44000 | R22: France | S22: Labrune Janine | T22: Small | U22: =Auto[[#This Row],[SALES]]-(Auto[[#This Row],[MSRP]]*Auto[[#This Row],[ORDER QUANTITY]]) -> -1261.89 | V22: =Auto[[#This Row],[PROFIT]]/100 -> -12.6189
A23: 10388 | B23: 42 | C23: 76.36 | D23: 4 | E23: 3207.12 | F23: 43893 | G23: March | H23: 4months | I23: Shipped | J23: Motorcycles | K23: 95 | L23: S10_1678 | N23: 5085552555 | O23: 1785 First Street | P23: New Bedford | Q23: 50553 | R23: USA | S23: Benitez Violeta | T23: Medium | U23: =Auto[[#This Row],[SALES]]-(Auto[[#This Row],[MSRP]]*Auto[[#This Row],[ORDER QUANTITY]]) -> -782.88 | V23: =Auto[[#This Row],[PROFIT]]/100 -> -7.8288
A24: 10403 | B24: 24 | C24: 101.44 | D24: 7 | E24: 2434.56 | F24: 43929 | G24: April | H24: 3months | I24: Shipped | J24: Motorcycles | K24: 95 | L24: S10_1678 | N24: (171) 555-2282 | O24: Berkeley Gardens 12 Brewery | P24: Liverpool | Q24: WX1 6LT | R24: UK | S24: Devon Elizabeth | T24: Small | U24: =Auto[[#This Row],[SALES]]-(Auto[[#This Row],[MSRP]]*Auto[[#This Row],[ORDER QUANTITY]]) -> 154.56 | V24: =Auto[[#This Row],[PROFIT]]/100 -> 1.5456
A25: 10417 | B25: 66 | C25: 113.88 | D25: 2 | E25: 7516.08 | F25: 43964 | G25: May | H25: 1months | I25: Disputed | J25: Motorcycles | K25: 95 | L25: S10_1678 | N25: (91) 555 94 44 | O25: C/ Moralzarzal, 86 | P25: Madrid | Q25: 28034 | R25: Spain | S25: Freyre Diego | T25: Large | U25: =Auto[[#This Row],[SALES]]-(Auto[[#This Row],[MSRP]]*Auto[[#This Row],[ORDER QUANTITY]]) -> 1246.08 | V25: =Auto[[#This Row],[PROFIT]]/100 -> 12.4608
A26: 10103 | B26: 26 | C26: 207.87 | D26: 11 | E26: 5404.62 | F26: 43129 | G26: January | H26: 29months | I26: Shipped | J26: Classic Cars | K26: 214 | L26: S10_1949 | N26: 07-98 9555 | O26: Erling Skakkes gate 78 | P26: Stavern | Q26: 4110 | R26: Norway | S26: Bergulfsen Jonas | T26: Medium | U26: =Auto[[#This Row],[SALES]]-(Auto[[#This Row],[MSRP]]*Auto[[#This Row],[ORDER QUANTITY]]) -> -159.38 | V26: =Auto[[#This Row],[PROFIT]]/100 -> -1.5938
A27: 10112 | B27: 29 | C27: 248.59 | D27: 1 | E27: 7209.11 | F27: 43183 | G27: March | H27: 28months | I27: Shipped | J27: Classic Cars | K27: 214 | L27: S10_1949 | N27: 0921-12 3555 | O27: BerguvsvÂ„gen 8 | P27: Lule | Q27: S-958 22 | R27: Sweden | S27: Berglund Christina | T27: Large | U27: =Auto[[#This Row],[SALES]]-(Auto[[#This Row],[MSRP]]*Auto[[#This Row],[ORDER QUANTITY]]) -> 1003.11 | V27: =Auto[[#This Row],[PROFIT]]/100 -> 10.0311
A28: 10126 | B28: 38 | C28: 192.87 | D28: 11 | E28: 7329.06 | F28: 43248 | G28: May | H28: 25months | I28: Shipped | J28: Classic Cars | K28: 214 | L28: S10_1949 | N28: (91) 555 22 82 | O28: C/ Araquil, 67 | P28: Madrid | Q28: 28023 | R28: Spain | S28: Sommer MartÂ¡n | T28: Large | U28: =Auto[[#This Row],[SALES]]-(Auto[[#This Row],[MSRP]]*Auto[[#This Row],[ORDER QUANTITY]]) -> -802.94 | V28: =Auto[[#This Row],[PROFIT]]/100 -> -8.0294
A29: 10140 | B29: 37 | C29: 199.3 | D29: 11 | E29: 7374.1 | F29: 43305 | G29: July | H29: 24months | I29: Shipped | J29: Classic Cars | K29: 214 | L29: S10_1949 | N29: 6505556809 | O29: 9408 Furth Circle | P29: Burlingame | Q29: 94217 | R29: USA | S29: Hirano Juri | T29: Large | U29: =Auto[[#This Row],[SALES]]-(Auto[[#This Row],[MSRP]]*Auto[[#This Row],[ORDER QUANTITY]]) -> -543.9 | V29: =Auto[[#This Row],[PROFIT]]/100 -> -5.439
A30: 10150 | B30: 45 | C30: 244.3 | D30: 8 | E30: 10993.5 | F30: 43362 | G30: September | H30: 22months | I30: Shipped | J30: Classic Cars | K30: 214 | L30: S10_1949 | N30: +65 221 7555 | O30: Bronz Sok., Bronz Apt. 3/6 Tesvikiye | P30: Singapore | Q30: 79903 | R30: Singapore | S30: Natividad Eric | T30: Large | U30: =Auto[[#This Row],[SALES]]-(Auto[[#This Row],[MSRP]]*Auto[[#This Row],[ORDER QUANTITY]]) -> 1363.5 | V30: =Auto[[#This Row],[PROFIT]]/100 -> 13.635
A31: 10163 | B31: 21 | C31: 231.44 | D31: 1 | E31: 4860.24 | F31: 43393 | G31: October | H31: 21months | I31: Shipped | J31: Classic Cars | K31: 214 | L31: S10_1949 | N31: 2125558493 | O31: 5905 Pompton St. | P31: NYC | Q31: 10022 | R31: USA | S31: Hernandez Maria | T31: Medium | U31: =Auto[[#This Row],[SALES]]-(Auto[[#This Row],[MSRP]]*Auto[[#This Row],[ORDER QUANTITY]]) -> 366.24 | V31: =Auto[[#This Row],[PROFIT]]/100 -> 3.6624
A32: 10174 | B32: 34 | C32: 235.73 | D32: 4 | E32: 8014.82 | F32: 43410 | G32: November | H32: 20months | I32: Shipped | J32: Classic Cars | K32: 214 | L32: S10_1949 | N32: 61-7-3844-6555 | O32: 31 Duncan St. West End | P32: South Brisbane | Q32: 4101 | R32: Australia | S32: Calaghan Tony | T32: Large | U32: =Auto[[#This Row],[SALES]]-(Auto[[#This Row],[MSRP]]*Auto[[#This Row],[ORDER QUANTITY]]) -> 738.82 | V32: =Auto[[#This Row],[PROFIT]]/100 -> 7.3882
A33: 10183 | B33: 23 | C33: 233.59 | D33: 8 | E33: 5372.57 | F33: 43417 | G33: November | H33: 20months | I33: Shipped | J33: Classic Cars | K33: 214 | L33: S10_1949 | N33: 2155554695 | O33: 782 First Street | P33: Philadelphia | Q33: 71270 | R33: USA | S33: Cervantes Francisca | T33: Medium | U33: =Auto[[#This Row],[SALES]]-(Auto[[#This Row],[MSRP]]*Auto[[#This Row],[ORDER QUANTITY]]) -> 450.57 | V33: =Auto[[#This Row],[PROFIT]]/100 -> 4.5057
A34: 10194 | B34: 42 | C34: 173.58 | D34: 11 | E34: 7290.36 | F34: 43429 | G34: November | H34: 20months | I34: Shipped | J34: Classic Cars | K34: 214 | L34: S10_1949 | N34: 78.32.5555 | O34: 2, rue du Commerce | P34: Lyon | Q34: 69004 | R34: France | S34: Saveley Mary | T34: Large | U34: =Auto[[#This Row],[SALES]]-(Auto[[#This Row],[MSRP]]*Auto[[#This Row],[ORDER QUANTITY]]) -> -1697.64 | V34: =Auto[[#This Row],[PROFIT]]/100 -> -16.9764
A35: 10206 | B35: 47 | C35: 192.87 | D35: 6 | E35: 9064.89 | F35: 43439 | G35: December | H35: 19months | I35: Shipped | J35: Classic Cars | K35: 214 | L35: S10_1949 | N35: (604) 555-3392 | O35: 1900 Oak St. | P35: Vancouver | Q35: V3F 2K1 | R35: Canada | S35: Tannamuri Yoshi | T35: Large | U35: =Auto[[#This Row],[SALES]]-(Auto[[#This Row],[MSRP]]*Auto[[#This Row],[ORDER QUANTITY]]) -> -993.11 | V35: =Auto[[#This Row],[PROFIT]]/100 -> -9.9311
A36: 10215 | B36: 35 | C36: 173.58 | D36: 3 | E36: 6075.3 | F36: 43494 | G36: January | H36: 17months | I36: Shipped | J36: Classic Cars | K36: 214 | L36: S10_1949 | N36: 3105553722 | O36: 3675 Furth Circle | P36: Burbank | Q36: 94019 | R36: USA | S36: Thompson Steve | T36: Medium | U36: =Auto[[#This Row],[SALES]]-(Auto[[#This Row],[MSRP]]*Auto[[#This Row],[ORDER QUANTITY]]) -> -1414.7 | V36: =Auto[[#This Row],[PROFIT]]/100 -> -14.147
A37: 10228 | B37: 29 | C37: 222.87 | D37: 2 | E37: 6463.23 | F37: 43534 | G37: March | H37: 16months | I37: Shipped | J37: Classic Cars | K37: 214 | L37: S10_1949 | N37: 6175555555 | O37: 4658 Baden Av. | P37: Cambridge | Q37: 51247 | R37: USA | S37: Tseng Kyung | T37: Medium | U37: =Auto[[#This Row],[SALES]]-(Auto[[#This Row],[MSRP]]*Auto[[#This Row],[ORDER QUANTITY]]) -> 257.23 | V37: =Auto[[#This Row],[PROFIT]]/100 -> 2.5723
A38: 10245 | B38: 34 | C38: 180.01 | D38: 9 | E38: 6120.34 | F38: 43589 | G38: May | H38: 14months | I38: Shipped | J38: Classic Cars | K38: 214 | L38: S10_1949 | N38: 2035559545 | O38: 567 North Pendale Street | P38: New Haven | Q38: 97823 | R38: USA | S38: Murphy Leslie | T38: Medium | U38: =Auto[[#This Row],[SALES]]-(Auto[[#This Row],[MSRP]]*Auto[[#This Row],[ORDER QUANTITY]]) -> -1155.66 | V38: =Auto[[#This Row],[PROFIT]]/100 -> -11.5566
A39: 10258 | B39: 32 | C39: 240.02 | D39: 6 | E39: 7680.64 | F39: 43631 | G39: June | H39: 13months | I39: Shipped | J39: Classic Cars | K39: 214 | L39: S10_1949 | N39: +81 3 3584 0555 | O39: 2-2-8 Roppongi | P39: Minato-ku | Q39: 106-0032 | R39: Japan | S39: Shimamura Akiko | T39: Large | U39: =Auto[[#This Row],[SALES]]-(Auto[[#This Row],[MSRP]]*Auto[[#This Row],[ORDER QUANTITY]]) -> 832.64 | V39: =Auto[[#This Row],[PROFIT]]/100 -> 8.3264
A40: 10270 | B40: 21 | C40: 233.59 | D40: 9 | E40: 4905.39 | F40: 43665 | G40: July | H40: 12months | I40: Shipped | J40: Classic Cars | K40: 214 | L40: S10_1949 | N40: +61 2 9495 8555 | O40: Monitor Money Building, 815 Pacific Hwy | P40: Chatswood | Q40: 2067 | R40: Australia | S40: Huxley Adrian | T40: Medium | U40: =Auto[[#This Row],[SALES]]-(Auto[[#This Row],[MSRP]]*Auto[[#This Row],[ORDER QUANTITY]]) -> 411.39 | V40: =Auto[[#This Row],[PROFIT]]/100 -> 4.1139
A41: 10280 | B41: 34 | C41: 235.73 | D41: 2 | E41: 8014.82 | F41: 43694 | G41: August | H41: 11months | I41: Shipped | J41: Classic Cars | K41: 214 | L41: S10_1949 | N41: 011-4988555 | O41: Via Monte Bianco 34 | P41: Torino | Q41: 10100 | R41: Italy | S41: Accorti Paolo | T41: Large | U41: =Auto[[#This Row],[SALES]]-(Auto[[#This Row],[MSRP]]*Auto[[#This Row],[ORDER QUANTITY]]) -> 738.82 | V41: =Auto[[#This Row],[PROFIT]]/100 -> 7.3882
A42: 10291 | B42: 37 | C42: 192.87 | D42: 11 | E42: 7136.19 | F42: 43716 | G42: September | H42: 10months | I42: Shipped | J42: Classic Cars | K42: 214 | L42: S10_1949 | N42: 0695-34 6555 | O42: ?kergatan 24 | P42: Boras | Q42: S-844 67 | R42: Sweden | S42: Larsson Maria | T42: Large | U42: =Auto[[#This Row],[SALES]]-(Auto[[#This Row],[MSRP]]*Auto[[#This Row],[ORDER QUANTITY]]) -> -781.81 | V42: =Auto[[#This Row],[PROFIT]]/100 -> -7.8181
A43: 10304 | B43: 47 | C43: 216.44 | D43: 6 | E43: 10172.7 | F43: 43749 | G43: October | H43: 9months | I43: Shipped | J43: Classic Cars | K43: 214 | L43: S10_1949 | N43: 30.59.8555 | O43: 67, avenue de l'Europe | P43: Versailles | Q43: 78000 | R43: France | S43: Tonini Daniel | T43: Large | U43: =Auto[[#This Row],[SALES]]-(Auto[[#This Row],[MSRP]]*Auto[[#This Row],[ORDER QUANTITY]]) -> 114.7 | V43: =Auto[[#This Row],[PROFIT]]/100 -> 1.147
A44: 10312 | B44: 48 | C44: 242.16 | D44: 3 | E44: 11623.7 | F44: 43759 | G44: October | H44: 9months | I44: Shipped | J44: Classic Cars | K44: 214 | L44: S10_1949 | N44: 4155551450 | O44: 5677 Strong St. | P44: San Rafael | Q44: 97562 | R44: USA | S44: Nelson Valarie | T44: Large | U44: =Auto[[#This Row],[SALES]]-(Auto[[#This Row],[MSRP]]*Auto[[#This Row],[ORDER QUANTITY]]) -> 1351.7 | V44: =Auto[[#This Row],[PROFIT]]/100 -> 13.517
A45: 10322 | B45: 40 | C45: 150.01 | D45: 1 | E45: 6000.4 | F45: 43773 | G45: November | H45: 8months | I45: Shipped | J45: Classic Cars | K45: 214 | L45: S10_1949 | N45: 6035558647 | O45: 2304 Long Airport Avenue | P45: Nashua | Q45: 62005 | R45: USA | S45: Young Valarie | T45: Medium | U45: =Auto[[#This Row],[SALES]]-(Auto[[#This Row],[MSRP]]*Auto[[#This Row],[ORDER QUANTITY]]) -> -2559.6 | V45: =Auto[[#This Row],[PROFIT]]/100 -> -25.596
A46: 10347 | B46: 30 | C46: 131.49 | D46: 1 | E46: 3944.7 | F46: 43798 | G46: November | H46: 8months | I46: Shipped | J46: Classic Cars | K46: 214 | L46: S10_1949 | N46: 03 9520 4555 | O46: 636 St Kilda Road | P46: Melbourne | Q46: 3004 | R46: Australia | S46: Ferguson Peter | T46: Medium | U46: =Auto[[#This Row],[SALES]]-(Auto[[#This Row],[MSRP]]*Auto[[#This Row],[ORDER QUANTITY]]) -> -2475.3 | V46: =Auto[[#This Row],[PROFIT]]/100 -> -24.753
A47: 10357 | B47: 32 | C47: 177.87 | D47: 10 | E47: 5691.84 | F47: 43809 | G47: December | H47: 7months | I47: Shipped | J47: Classic Cars | K47: 214 | L47: S10_1949 | N47: 4155551450 | O47: 5677 Strong St. | P47: San Rafael | Q47: 97562 | R47: USA | S47: Nelson Valarie | T47: Medium | U47: =Auto[[#This Row],[SALES]]-(Auto[[#This Row],[MSRP]]*Auto[[#This Row],[ORDER QUANTITY]]) -> -1156.16 | V47: =Auto[[#This Row],[PROFIT]]/100 -> -11.5616
A48: 10369 | B48: 41 | C48: 110.12 | D48: 2 | E48: 4514.92 | F48: 43850 | G48: January | H48: 6months | I48: Shipped | J48: Classic Cars | K48: 214 | L48: S10_1949 | N48: 6175558555 | O48: 7825 Douglas Av. | P48: Brickhaven | Q48: 58339 | R48: USA | S48: Nelson Allen | T48: Medium | U48: =Auto[[#This Row],[SALES]]-(Auto[[#This Row],[MSRP]]*Auto[[#This Row],[ORDER QUANTITY]]) -> -4259.08 | V48: =Auto[[#This Row],[PROFIT]]/100 -> -42.5908
A49: 10391 | B49: 24 | C49: 100.69 | D49: 4 | E49: 2416.56 | F49: 43899 | G49: March | H49: 4months | I49: Shipped | J49: Classic Cars | K49: 214 | L49: S10_1949 | N49: 02 9936 8555 | O49: 201 Miller Street | P49: North Sydney | Q49: 2060 | R49: Australia | S49: O'Hara Anna | T49: Small | U49: =Auto[[#This Row],[SALES]]-(Auto[[#This Row],[MSRP]]*Auto[[#This Row],[ORDER QUANTITY]]) -> -2719.44 | V49: =Auto[[#This Row],[PROFIT]]/100 -> -27.1944
A50: 10411 | B50: 23 | C50: 180.01 | D50: 9 | E50: 4140.23 | F50: 43952 | G50: May | H50: 3months | I50: Shipped | J50: Classic Cars | K50: 214 | L50: S10_1949 | N50: (514) 555-8054 | O50: 43 rue St. Laurent | P50: Montreal | Q50: H1J 1C3 | R50: Canada | S50: Fresnisre Jean | T50: Medium | U50: =Auto[[#This Row],[SALES]]-(Auto[[#This Row],[MSRP]]*Auto[[#This Row],[ORDER QUANTITY]]) -> -781.77 | V50: =Auto[[#This Row],[PROFIT]]/100 -> -7.8177
A51: 10424 | B51: 50 | C51: 240.02 | D51: 6 | E51: 12001 | F51: 43982 | G51: May | H51: 2months | I51: In Process | J51: Classic Cars | K51: 214 | L51: S10_1949 | N51: (91) 555 94 44 | O51: C/ Moralzarzal, 86 | P51: Madrid | Q51: 28034 | R51: Spain | S51: Freyre Diego | T51: Large | U51: =Auto[[#This Row],[SALES]]-(Auto[[#This Row],[MSRP]]*Auto[[#This Row],[ORDER QUANTITY]]) -> 1301 | V51: =Auto[[#This Row],[PROFIT]]/100 -> 13.01
A52: 10107 | B52: 39 | C52: 99.91 | D52: 5 | E52: 3896.49 | F52: 43155 | G52: February | H52: 29months | I52: Shipped | J52: Motorcycles | K52: 118 | L52: S10_2016 | N52: 2125557818 | O52: 897 Long Airport Avenue | P52: NYC | Q52: 10022 | R52: USA | S52: Yu Kwai | T52: Medium | U52: =Auto[[#This Row],[SALES]]-(Auto[[#This Row],[MSRP]]*Auto[[#This Row],[ORDER QUANTITY]]) -> -705.51 | V52: =Auto[[#This Row],[PROFIT]]/100 -> -7.0551
A53: 10120 | B53: 29 | C53: 96.34 | D53: 3 | E53: 2793.86 | F53: 43219 | G53: April | H53: 27months | I53: Shipped | J53: Motorcycles | K53: 118 | L53: S10_2016 | N53: 03 9520 4555 | O53: 636 St Kilda Road | P53: Melbourne | Q53: 3004 | R53: Australia | S53: Ferguson Peter | T53: Small | U53: =Auto[[#This Row],[SALES]]-(Auto[[#This Row],[MSRP]]*Auto[[#This Row],[ORDER QUANTITY]]) -> -628.14 | V53: =Auto[[#This Row],[PROFIT]]/100 -> -6.2814
A54: 10134 | B54: 27 | C54: 122.51 | D54: 5 | E54: 3307.77 | F54: 43282 | G54: July | H54: 25months | I54: Shipped | J54: Motorcycles | K54: 118 | L54: S10_2016 | N54: +33 1 46 62 7555 | O54: 27 rue du Colonel Pierre Avia | P54: Paris | Q54: 75508 | R54: France | S54: Da Cunha Daniel | T54: Medium | U54: =Auto[[#This Row],[SALES]]-(Auto[[#This Row],[MSRP]]*Auto[[#This Row],[ORDER QUANTITY]]) -> 121.77 | V54: =Auto[[#This Row],[PROFIT]]/100 -> 1.2177
A55: 10145 | B55: 37 | C55: 140.35 | D55: 9 | E55: 5192.95 | F55: 43337 | G55: August | H55: 23months | I55: Shipped | J55: Motorcycles | K55: 118 | L55: S10_2016 | N55: 6265557265 | O55: 78934 Hillside Dr. | P55: Pasadena | Q55: 90003 | R55: USA | S55: Young Julie | T55: Medium | U55: =Auto[[#This Row],[SALES]]-(Auto[[#This Row],[MSRP]]*Auto[[#This Row],[ORDER QUANTITY]]) -> 826.95 | V55: =Auto[[#This Row],[PROFIT]]/100 -> 8.2695
A56: 10168 | B56: 27 | C56: 135.59 | D56: 4 | E56: 3660.93 | F56: 43401 | G56: October | H56: 21months | I56: Shipped | J56: Motorcycles | K56: 118 | L56: S10_2016 | N56: 6505556809 | O56: 9408 Furth Circle | P56: Burlingame | Q56: 94217 | R56: USA | S56: Hirano Juri | T56: Medium | U56: =Auto[[#This Row],[SALES]]-(Auto[[#This Row],[MSRP]]*Auto[[#This Row],[ORDER QUANTITY]]) -> 474.93 | V56: =Auto[[#This Row],[PROFIT]]/100 -> 4.7493
A57: 10180 | B57: 42 | C57: 111.8 | D57: 12 | E57: 4695.6 | F57: 43415 | G57: November | H57: 21months | I57: Shipped | J57: Motorcycles | K57: 118 | L57: S10_2016 | N57: 20.16.1555 | O57: 184, chausse de Tournai | P57: Lille | Q57: 59000 | R57: France | S57: Rance Martine | T57: Medium | U57: =Auto[[#This Row],[SALES]]-(Auto[[#This Row],[MSRP]]*Auto[[#This Row],[ORDER QUANTITY]]) -> -260.4 | V57: =Auto[[#This Row],[PROFIT]]/100 -> -2.604
A58: 10188 | B58: 38 | C58: 96.34 | D58: 4 | E58: 3660.92 | F58: 43422 | G58: November | H58: 21months | I58: Shipped | J58: Motorcycles | K58: 118 | L58: S10_2016 | N58: +47 2267 3215 | O58: Drammen 121, PR 744 Sentrum | P58: Bergen | Q58: N 5804 | R58: Norway | S58: Oeztan Veysel | T58: Medium | U58: =Auto[[#This Row],[SALES]]-(Auto[[#This Row],[MSRP]]*Auto[[#This Row],[ORDER QUANTITY]]) -> -823.08 | V58: =Auto[[#This Row],[PROFIT]]/100 -> -8.2308
A59: 10210 | B59: 23 | C59: 130.83 | D59: 2 | E59: 3009.09 | F59: 43477 | G59: January | H59: 19months | I59: Shipped | J59: Motorcycles | K59: 118 | L59: S10_2016 | N59: +81 06 6342 5555 | O59: Dojima Avanza 4F, 1-6-20 Dojima, Kita-ku | P59: Osaka | Q59: 530-0003 | R59: Japan | S59: Kentary Mory | T59: Medium | U59: =Auto[[#This Row],[SALES]]-(Auto[[#This Row],[MSRP]]*Auto[[#This Row],[ORDER QUANTITY]]) -> 295.09 | V59: =Auto[[#This Row],[PROFIT]]/100 -> 2.9509
A60: 10223 | B60: 47 | C60: 115.37 | D60: 4 | E60: 5422.39 | F60: 43516 | G60: February | H60: 18months | I60: Shipped | J60: Motorcycles | K60: 118 | L60: S10_2016 | N60: 03 9520 4555 | O60: 636 St Kilda Road | P60: Melbourne | Q60: 3004 | R60: Australia | S60: Ferguson Peter | T60: Medium | U60: =Auto[[#This Row],[SALES]]-(Auto[[#This Row],[MSRP]]*Auto[[#This Row],[ORDER QUANTITY]]) -> -123.61 | V60: =Auto[[#This Row],[PROFIT]]/100 -> -1.2361
A61: 10236 | B61: 22 | C61: 129.64 | D61: 1 | E61: 2852.08 | F61: 43558 | G61: April | H61: 16months | I61: Shipped | J61: Motorcycles | K61: 118 | L61: S10_2016 | N61: 2155559857 | O61: 11328 Douglas Av. | P61: Philadelphia | Q61: 71270 | R61: USA | S61: Hernandez Rosa | T61: Small | U61: =Auto[[#This Row],[SALES]]-(Auto[[#This Row],[MSRP]]*Auto[[#This Row],[ORDER QUANTITY]]) -> 256.08 | V61: =Auto[[#This Row],[PROFIT]]/100 -> 2.5608
A62: 10251 | B62: 44 | C62: 130.83 | D62: 5 | E62: 5756.52 | F62: 43603 | G62: May | H62: 15months | I62: Shipped | J62: Motorcycles | K62: 118 | L62: S10_2016 | N62: 2015559350 | O62: 7476 Moss Rd. | P62: Newark | Q62: 94019 | R62: USA | S62: Brown William | T62: Medium | U62: =Auto[[#This Row],[SALES]]-(Auto[[#This Row],[MSRP]]*Auto[[#This Row],[ORDER QUANTITY]]) -> 564.52 | V62: =Auto[[#This Row],[PROFIT]]/100 -> 5.6452
A63: 10263 | B63: 40 | C63: 111.8 | D63: 5 | E63: 4472 | F63: 43644 | G63: June | H63: 13months | I63: Shipped | J63: Motorcycles | K63: 118 | L63: S10_2016 | N63: 2035552570 | O63: 25593 South Bay Ln. | P63: Bridgewater | Q63: 97562 | R63: USA | S63: King Julie | T63: Medium | U63: =Auto[[#This Row],[SALES]]-(Auto[[#This Row],[MSRP]]*Auto[[#This Row],[ORDER QUANTITY]]) -> -248 | V63: =Auto[[#This Row],[PROFIT]]/100 -> -2.48
A64: 10275 | B64: 22 | C64: 132.02 | D64: 4 | E64: 2904.44 | F64: 43669 | G64: July | H64: 13months | I64: Shipped | J64: Motorcycles | K64: 118 | L64: S10_2016 | N64: 40.67.8555 | O64: 67, rue des Cinquante Otages | P64: Nantes | Q64: 44000 | R64: France | S64: Labrune Janine | T64: Small | U64: =Auto[[#This Row],[SALES]]-(Auto[[#This Row],[MSRP]]*Auto[[#This Row],[ORDER QUANTITY]]) -> 308.44 | V64: =Auto[[#This Row],[PROFIT]]/100 -> 3.0844
A65: 10285 | B65: 47 | C65: 137.97 | D65: 9 | E65: 6484.59 | F65: 43704 | G65: August | H65: 11months | I65: Shipped | J65: Motorcycles | K65: 118 | L65: S10_2016 | N65: 6175558555 | O65: 39323 Spinnaker Dr. | P65: Cambridge | Q65: 51247 | R65: USA | S65: Hernandez Marta | T65: Medium | U65: =Auto[[#This Row],[SALES]]-(Auto[[#This Row],[MSRP]]*Auto[[#This Row],[ORDER QUANTITY]]) -> 938.59 | V65: =Auto[[#This Row],[PROFIT]]/100 -> 9.3859
A66: 10298 | B66: 39 | C66: 96.34 | D66: 1 | E66: 3757.26 | F66: 43735 | G66: September | H66: 10months | I66: Shipped | J66: Motorcycles | K66: 118 | L66: S10_2016 | N66: 40.32.2555 | O66: 54, rue Royale | P66: Nantes | Q66: 44000 | R66: France | S66: Schmitt Carine | T66: Medium | U66: =Auto[[#This Row],[SALES]]-(Auto[[#This Row],[MSRP]]*Auto[[#This Row],[ORDER QUANTITY]]) -> -844.74 | V66: =Auto[[#This Row],[PROFIT]]/100 -> -8.4474
A67: 10308 | B67: 34 | C67: 118.94 | D67: 2 | E67: 4043.96 | F67: 43753 | G67: October | H67: 10months | I67: Shipped | J67: Motorcycles | K67: 118 | L67: S10_2016 | N67: 9145554562 | O67: 3758 North Pendale Street | P67: White Plains | Q67: 24067 | R67: USA | S67: Frick Steve | T67: Medium | U67: =Auto[[#This Row],[SALES]]-(Auto[[#This Row],[MSRP]]*Auto[[#This Row],[ORDER QUANTITY]]) -> 31.96 | V67: =Auto[[#This Row],[PROFIT]]/100 -> 0.3196
A68: 10318 | B68: 45 | C68: 123.7 | D68: 4 | E68: 5566.5 | F68: 43771 | G68: November | H68: 9months | I68: Shipped | J68: Motorcycles | K68: 118 | L68: S10_2016 | N68: 2155551555 | O68: 7586 Pompton St. | P68: Allentown | Q68: 70267 | R68: USA | S68: Yu Kyung | T68: Medium | U68: =Auto[[#This Row],[SALES]]-(Auto[[#This Row],[MSRP]]*Auto[[#This Row],[ORDER QUANTITY]]) -> 256.5 | V68: =Auto[[#This Row],[PROFIT]]/100 -> 2.565
A69: 10329 | B69: 20 | C69: 158.8 | D69: 2 | E69: 3176 | F69: 43784 | G69: November | H69: 9months | I69: Shipped | J69: Motorcycles | K69: 118 | L69: S10_2016 | N69: 2125557818 | O69: 897 Long Airport Avenue | P69: NYC | Q69: 10022 | R69: USA | S69: Yu Kwai | T69: Medium | U69: =Auto[[#This Row],[SALES]]-(Auto[[#This Row],[MSRP]]*Auto[[#This Row],[ORDER QUANTITY]]) -> 816 | V69: =Auto[[#This Row],[PROFIT]]/100 -> 8.16
A70: 10339 | B70: 40 | C70: 68.92 | D70: 4 | E70: 2756.8 | F70: 43792 | G70: November | H70: 9months | I70: Shipped | J70: Motorcycles | K70: 118 | L70: S10_2016 | N70: +81 3 3584 0555 | O70: 2-2-8 Roppongi | P70: Minato-ku | Q70: 106-0032 | R70: Japan | S70: Shimamura Akiko | T70: Small | U70: =Auto[[#This Row],[SALES]]-(Auto[[#This Row],[MSRP]]*Auto[[#This Row],[ORDER QUANTITY]]) -> -1963.2 | V70: =Auto[[#This Row],[PROFIT]]/100 -> -19.632
A71: 10361 | B71: 26 | C71: 51.15 | D71: 8 | E71: 1329.9 | F71: 43816 | G71: December | H71: 8months | I71: Shipped | J71: Motorcycles | K71: 118 | L71: S10_2016 | N71: +61 2 9495 8555 | O71: Monitor Money Building, 815 Pacific Hwy | P71: Chatswood | Q71: 2067 | R71: Australia | S71: Huxley Adrian | T71: Small | U71: =Auto[[#This Row],[SALES]]-(Auto[[#This Row],[MSRP]]*Auto[[#This Row],[ORDER QUANTITY]]) -> -1738.1 | V71: =Auto[[#This Row],[PROFIT]]/100 -> -17.381
A72: 10374 | B72: 39 | C72: 135.59 | D72: 5 | E72: 5288.01 | F72: 43863 | G72: February | H72: 6months | I72: Shipped | J72: Motorcycles | K72: 118 | L72: S10_2016 | N72: 61-7-3844-6555 | O72: 31 Duncan St. West End | P72: South Brisbane | Q72: 4101 | R72: Australia | S72: Calaghan Tony | T72: Medium | U72: =Auto[[#This Row],[SALES]]-(Auto[[#This Row],[MSRP]]*Auto[[#This Row],[ORDER QUANTITY]]) -> 686.01 | V72: =Auto[[#This Row],[PROFIT]]/100 -> 6.8601
A73: 10388 | B73: 50 | C73: 44.51 | D73: 5 | E73: 2225.5 | F73: 43893 | G73: March | H73: 5months | I73: Shipped | J73: Motorcycles | K73: 118 | L73: S10_2016 | N73: 5085552555 | O73: 1785 First Street | P73: New Bedford | Q73: 50553 | R73: USA | S73: Benitez Violeta | T73: Small | U73: =Auto[[#This Row],[SALES]]-(Auto[[#This Row],[MSRP]]*Auto[[#This Row],[ORDER QUANTITY]]) -> -3674.5 | V73: =Auto[[#This Row],[PROFIT]]/100 -> -36.745
A74: 10402 | B74: 45 | C74: 129.64 | D74: 1 | E74: 5833.8 | F74: 43928 | G74: April | H74: 4months | I74: Shipped | J74: Motorcycles | K74: 118 | L74: S10_2016 | N74: (1) 47.55.6555 | O74: 25, rue Lauriston | P74: Paris | Q74: 75016 | R74: France | S74: Perrier Dominique | T74: Medium | U74: =Auto[[#This Row],[SALES]]-(Auto[[#This Row],[MSRP]]*Auto[[#This Row],[ORDER QUANTITY]]) -> 523.8 | V74: =Auto[[#This Row],[PROFIT]]/100 -> 5.238
A75: 10417 | B75: 45 | C75: 130.83 | D75: 5 | E75: 5887.35 | F75: 43964 | G75: May | H75: 3months | I75: Disputed | J75: Motorcycles | K75: 118 | L75: S10_2016 | N75: (91) 555 94 44 | O75: C/ Moralzarzal, 86 | P75: Madrid | Q75: 28034 | R75: Spain | S75: Freyre Diego | T75: Medium | U75: =Auto[[#This Row],[SALES]]-(Auto[[#This Row],[MSRP]]*Auto[[#This Row],[ORDER QUANTITY]]) -> 577.35 | V75: =Auto[[#This Row],[PROFIT]]/100 -> 5.7735
A76: 10107 | B76: 27 | C76: 224.65 | D76: 4 | E76: 6065.55 | F76: 43155 | G76: February | H76: 30months | I76: Shipped | J76: Motorcycles | K76: 193 | L76: S10_4698 | N76: 2125557818 | O76: 897 Long Airport Avenue | P76: NYC | Q76: 10022 | R76: USA | S76: Yu Kwai | T76: Medium | U76: =Auto[[#This Row],[SALES]]-(Auto[[#This Row],[MSRP]]*Auto[[#This Row],[ORDER QUANTITY]]) -> 854.55 | V76: =Auto[[#This Row],[PROFIT]]/100 -> 8.5455
A77: 10120 | B77: 46 | C77: 201.41 | D77: 2 | E77: 9264.86 | F77: 43219 | G77: April | H77: 28months | I77: Shipped | J77: Motorcycles | K77: 193 | L77: S10_4698 | N77: 03 9520 4555 | O77: 636 St Kilda Road | P77: Melbourne | Q77: 3004 | R77: Australia | S77: Ferguson Peter | T77: Large | U77: =Auto[[#This Row],[SALES]]-(Auto[[#This Row],[MSRP]]*Auto[[#This Row],[ORDER QUANTITY]]) -> 386.86 | V77: =Auto[[#This Row],[PROFIT]]/100 -> 3.8686
A78: 10134 | B78: 31 | C78: 226.58 | D78: 4 | E78: 7023.98 | F78: 43282 | G78: July | H78: 26months | I78: Shipped | J78: Motorcycles | K78: 193 | L78: S10_4698 | N78: +33 1 46 62 7555 | O78: 27 rue du Colonel Pierre Avia | P78: Paris | Q78: 75508 | R78: France | S78: Da Cunha Daniel | T78: Large | U78: =Auto[[#This Row],[SALES]]-(Auto[[#This Row],[MSRP]]*Auto[[#This Row],[ORDER QUANTITY]]) -> 1040.98 | V78: =Auto[[#This Row],[PROFIT]]/100 -> 10.4098
A79: 10145 | B79: 33 | C79: 156.86 | D79: 8 | E79: 5176.38 | F79: 43337 | G79: August | H79: 24months | I79: Shipped | J79: Motorcycles | K79: 193 | L79: S10_4698 | N79: 6265557265 | O79: 78934 Hillside Dr. | P79: Pasadena | Q79: 90003 | R79: USA | S79: Young Julie | T79: Medium | U79: =Auto[[#This Row],[SALES]]-(Auto[[#This Row],[MSRP]]*Auto[[#This Row],[ORDER QUANTITY]]) -> -1192.62 | V79: =Auto[[#This Row],[PROFIT]]/100 -> -11.9262
A80: 10168 | B80: 20 | C80: 209.15 | D80: 3 | E80: 4183 | F80: 43401 | G80: October | H80: 22months | I80: Shipped | J80: Motorcycles | K80: 193 | L80: S10_4698 | N80: 6505556809 | O80: 9408 Furth Circle | P80: Burlingame | Q80: 94217 | R80: USA | S80: Hirano Juri | T80: Medium | U80: =Auto[[#This Row],[SALES]]-(Auto[[#This Row],[MSRP]]*Auto[[#This Row],[ORDER QUANTITY]]) -> 323 | V80: =Auto[[#This Row],[PROFIT]]/100 -> 3.23
A81: 10180 | B81: 41 | C81: 216.9 | D81: 11 | E81: 8892.9 | F81: 43415 | G81: November | H81: 22months | I81: Shipped | J81: Motorcycles | K81: 193 | L81: S10_4698 | N81: 20.16.1555 | O81: 184, chausse de Tournai | P81: Lille | Q81: 59000 | R81: France | S81: Rance Martine | T81: Large | U81: =Auto[[#This Row],[SALES]]-(Auto[[#This Row],[MSRP]]*Auto[[#This Row],[ORDER QUANTITY]]) -> 979.9 | V81: =Auto[[#This Row],[PROFIT]]/100 -> 9.799
A82: 10188 | B82: 45 | C82: 193.66 | D82: 3 | E82: 8714.7 | F82: 43422 | G82: November | H82: 21months | I82: Shipped | J82: Motorcycles | K82: 193 | L82: S10_4698 | N82: +47 2267 3215 | O82: Drammen 121, PR 744 Sentrum | P82: Bergen | Q82: N 5804 | R82: Norway | S82: Oeztan Veysel | T82: Large | U82: =Auto[[#This Row],[SALES]]-(Auto[[#This Row],[MSRP]]*Auto[[#This Row],[ORDER QUANTITY]]) -> 29.7 | V82: =Auto[[#This Row],[PROFIT]]/100 -> 0.297
A83: 10210 | B83: 34 | C83: 180.1 | D83: 1 | E83: 6123.4 | F83: 43477 | G83: January | H83: 20months | I83: Shipped | J83: Motorcycles | K83: 193 | L83: S10_4698 | N83: +81 06 6342 5555 | O83: Dojima Avanza 4F, 1-6-20 Dojima, Kita-ku | P83: Osaka | Q83: 530-0003 | R83: Japan | S83: Kentary Mory | T83: Medium | U83: =Auto[[#This Row],[SALES]]-(Auto[[#This Row],[MSRP]]*Auto[[#This Row],[ORDER QUANTITY]]) -> -438.6 | V83: =Auto[[#This Row],[PROFIT]]/100 -> -4.386
A84: 10223 | B84: 49 | C84: 199.47 | D84: 3 | E84: 9774.03 | F84: 43516 | G84: February | H84: 18months | I84: Shipped | J84: Motorcycles | K84: 193 | L84: S10_4698 | N84: 03 9520 4555 | O84: 636 St Kilda Road | P84: Melbourne | Q84: 3004 | R84: Australia | S84: Ferguson Peter | T84: Large | U84: =Auto[[#This Row],[SALES]]-(Auto[[#This Row],[MSRP]]*Auto[[#This Row],[ORDER QUANTITY]]) -> 317.03 | V84: =Auto[[#This Row],[PROFIT]]/100 -> 3.1703
A85: 10237 | B85: 39 | C85: 180.1 | D85: 9 | E85: 7023.9 | F85: 43560 | G85: April | H85: 17months | I85: Shipped | J85: Motorcycles | K85: 193 | L85: S10_4698 | N85: 2125551500 | O85: 2678 Kingston Rd. | P85: NYC | Q85: 10022 | R85: USA | S85: Frick Michael | T85: Large | U85: =Auto[[#This Row],[SALES]]-(Auto[[#This Row],[MSRP]]*Auto[[#This Row],[ORDER QUANTITY]]) -> -503.1 | V85: =Auto[[#This Row],[PROFIT]]/100 -> -5.031
A86: 10251 | B86: 43 | C86: 164.61 | D86: 4 | E86: 7078.23 | F86: 43603 | G86: May | H86: 15months | I86: Shipped | J86: Motorcycles | K86: 193 | L86: S10_4698 | N86: 2015559350 | O86: 7476 Moss Rd. | P86: Newark | Q86: 94019 | R86: USA | S86: Brown William | T86: Large | U86: =Auto[[#This Row],[SALES]]-(Auto[[#This Row],[MSRP]]*Auto[[#This Row],[ORDER QUANTITY]]) -> -1220.77 | V86: =Auto[[#This Row],[PROFIT]]/100 -> -12.2077
A87: 10263 | B87: 41 | C87: 203.34 | D87: 4 | E87: 8336.94 | F87: 43644 | G87: June | H87: 14months | I87: Shipped | J87: Motorcycles | K87: 193 | L87: S10_4698 | N87: 2035552570 | O87: 25593 South Bay Ln. | P87: Bridgewater | Q87: 97562 | R87: USA | S87: King Julie | T87: Large | U87: =Auto[[#This Row],[SALES]]-(Auto[[#This Row],[MSRP]]*Auto[[#This Row],[ORDER QUANTITY]]) -> 423.94 | V87: =Auto[[#This Row],[PROFIT]]/100 -> 4.2394
A88: 10275 | B88: 36 | C88: 191.72 | D88: 3 | E88: 6901.92 | F88: 43669 | G88: July | H88: 13months | I88: Shipped | J88: Motorcycles | K88: 193 | L88: S10_4698 | N88: 40.67.8555 | O88: 67, rue des Cinquante Otages | P88: Nantes | Q88: 44000 | R88: France | S88: Labrune Janine | T88: Medium | U88: =Auto[[#This Row],[SALES]]-(Auto[[#This Row],[MSRP]]*Auto[[#This Row],[ORDER QUANTITY]]) -> -46.08 | V88: =Auto[[#This Row],[PROFIT]]/100 -> -0.4608
A89: 10285 | B89: 27 | C89: 201.41 | D89: 8 | E89: 5438.07 | F89: 43704 | G89: August | H89: 12months | I89: Shipped | J89: Motorcycles | K89: 193 | L89: S10_4698 | N89: 6175558555 | O89: 39323 Spinnaker Dr. | P89: Cambridge | Q89: 51247 | R89: USA | S89: Hernandez Marta | T89: Medium | U89: =Auto[[#This Row],[SALES]]-(Auto[[#This Row],[MSRP]]*Auto[[#This Row],[ORDER QUANTITY]]) -> 227.07 | V89: =Auto[[#This Row],[PROFIT]]/100 -> 2.2707
A90: 10299 | B90: 29 | C90: 230.46 | D90: 11 | E90: 6683.34 | F90: 43738 | G90: September | H90: 11months | I90: Shipped | J90: Motorcycles | K90: 193 | L90: S10_4698 | N90: 90-224 8555 | O90: Keskuskatu 45 | P90: Helsinki | Q90: 21240 | R90: Finland | S90: Karttunen Matti | T90: Medium | U90: =Auto[[#This Row],[SALES]]-(Auto[[#This Row],[MSRP]]*Auto[[#This Row],[ORDER QUANTITY]]) -> 1086.34 | V90: =Auto[[#This Row],[PROFIT]]/100 -> 10.8634
A91: 10308 | B91: 20 | C91: 228.52 | D91: 1 | E91: 4570.4 | F91: 43753 | G91: October | H91: 11months | I91: Shipped | J91: Motorcycles | K91: 193 | L91: S10_4698 | N91: 9145554562 | O91: 3758 North Pendale Street | P91: White Plains | Q91: 24067 | R91: USA | S91: Frick Steve | T91: Medium | U91: =Auto[[#This Row],[SALES]]-(Auto[[#This Row],[MSRP]]*Auto[[#This Row],[ORDER QUANTITY]]) -> 710.4 | V91: =Auto[[#This Row],[PROFIT]]/100 -> 7.104
A92: 10318 | B92: 37 | C92: 207.22 | D92: 3 | E92: 7667.14 | F92: 43771 | G92: November | H92: 10months | I92: Shipped | J92: Motorcycles | K92: 193 | L92: S10_4698 | N92: 2155551555 | O92: 7586 Pompton St. | P92: Allentown | Q92: 70267 | R92: USA | S92: Yu Kyung | T92: Large | U92: =Auto[[#This Row],[SALES]]-(Auto[[#This Row],[MSRP]]*Auto[[#This Row],[ORDER QUANTITY]]) -> 526.14 | V92: =Auto[[#This Row],[PROFIT]]/100 -> 5.2614
A93: 10329 | B93: 26 | C93: 225.7 | D93: 3 | E93: 5868.2 | F93: 43784 | G93: November | H93: 10months | I93: Shipped | J93: Motorcycles | K93: 193 | L93: S10_4698 | N93: 2125557818 | O93: 897 Long Airport Avenue | P93: NYC | Q93: 10022 | R93: USA | S93: Yu Kwai | T93: Medium | U93: =Auto[[#This Row],[SALES]]-(Auto[[#This Row],[MSRP]]*Auto[[#This Row],[ORDER QUANTITY]]) -> 850.2 | V93: =Auto[[#This Row],[PROFIT]]/100 -> 8.502
A94: 10339 | B94: 39 | C94: 76.67 | D94: 3 | E94: 2990.13 | F94: 43792 | G94: November | H94: 9months | I94: Shipped | J94: Motorcycles | K94: 193 | L94: S10_4698 | N94: +81 3 3584 0555 | O94: 2-2-8 Roppongi | P94: Minato-ku | Q94: 106-0032 | R94: Japan | S94: Shimamura Akiko | T94: Small | U94: =Auto[[#This Row],[SALES]]-(Auto[[#This Row],[MSRP]]*Auto[[#This Row],[ORDER QUANTITY]]) -> -4536.87 | V94: =Auto[[#This Row],[PROFIT]]/100 -> -45.3687
A95: 10362 | B95: 22 | C95: 166.55 | D95: 4 | E95: 3664.1 | F95: 43835 | G95: January | H95: 8months | I95: Shipped | J95: Motorcycles | K95: 193 | L95: S10_4698 | N95: 6505556809 | O95: 9408 Furth Circle | P95: Burlingame | Q95: 94217 | R95: USA | S95: Hirano Juri | T95: Medium | U95: =Auto[[#This Row],[SALES]]-(Auto[[#This Row],[MSRP]]*Auto[[#This Row],[ORDER QUANTITY]]) -> -581.9 | V95: =Auto[[#This Row],[PROFIT]]/100 -> -5.819
A96: 10374 | B96: 22 | C96: 174.29 | D96: 1 | E96: 3834.38 | F96: 43863 | G96: February | H96: 7months | I96: Shipped | J96: Motorcycles | K96: 193 | L96: S10_4698 | N96: 61-7-3844-6555 | O96: 31 Duncan St. West End | P96: South Brisbane | Q96: 4101 | R96: Australia | S96: Calaghan Tony | T96: Medium | U96: =Auto[[#This Row],[SALES]]-(Auto[[#This Row],[MSRP]]*Auto[[#This Row],[ORDER QUANTITY]]) -> -411.62 | V96: =Auto[[#This Row],[PROFIT]]/100 -> -4.1162
A97: 10388 | B97: 21 | C97: 86.77 | D97: 7 | E97: 1822.17 | F97: 43893 | G97: March | H97: 6months | I97: Shipped | J97: Motorcycles | K97: 193 | L97: S10_4698 | N97: 5085552555 | O97: 1785 First Street | P97: New Bedford | Q97: 50553 | R97: USA | S97: Benitez Violeta | T97: Small | U97: =Auto[[#This Row],[SALES]]-(Auto[[#This Row],[MSRP]]*Auto[[#This Row],[ORDER QUANTITY]]) -> -2230.83 | V97: =Auto[[#This Row],[PROFIT]]/100 -> -22.3083
A98: 10403 | B98: 66 | C98: 180.1 | D98: 9 | E98: 11886.6 | F98: 43929 | G98: April | H98: 5months | I98: Shipped | J98: Motorcycles | K98: 193 | L98: S10_4698 | N98: (171) 555-2282 | O98: Berkeley Gardens 12 Brewery | P98: Liverpool | Q98: WX1 6LT | R98: UK | S98: Devon Elizabeth | T98: Large | U98: =Auto[[#This Row],[SALES]]-(Auto[[#This Row],[MSRP]]*Auto[[#This Row],[ORDER QUANTITY]]) -> -851.4 | V98: =Auto[[#This Row],[PROFIT]]/100 -> -8.514
A99: 10417 | B99: 56 | C99: 164.61 | D99: 4 | E99: 9218.16 | F99: 43964 | G99: May | H99: 4months | I99: Disputed | J99: Motorcycles | K99: 193 | L99: S10_4698 | N99: (91) 555 94 44 | O99: C/ Moralzarzal, 86 | P99: Madrid | Q99: 28034 | R99: Spain | S99: Freyre Diego | T99: Large | U99: =Auto[[#This Row],[SALES]]-(Auto[[#This Row],[MSRP]]*Auto[[#This Row],[ORDER QUANTITY]]) -> -1589.84 | V99: =Auto[[#This Row],[PROFIT]]/100 -> -15.8984
A100: 10105 | B100: 50 | C100: 144.16 | D100: 2 | E100: 7208 | F100: 43142 | G100: February | H100: 31months | I100: Shipped | J100: Classic Cars | K100: 136 | L100: S10_4757 | N100: 31 12 3555 | O100: Vinb'ltet 34 | P100: Kobenhavn | Q100: 1734 | R100: Denmark | S100: Petersen Jytte | T100: Large | U100: =Auto[[#This Row],[SALES]]-(Auto[[#This Row],[MSRP]]*Auto[[#This Row],[ORDER QUANTITY]]) -> 408 | V100: =Auto[[#This Row],[PROFIT]]/100 -> 4.08
...

Sheet Pivot Analysis
Y1: COUNTRY | Z1: Denmark | BC1: USA
Y2: STATUS | Z2: Resolved | BC2: France
B3: Sum of SALES | D3: Months (ORDERDATE) | BC3: Norway | BD3: Shipped
B4: COUNTRY | C4: PRODUCTLINE | D4: Jan | E4: Feb | F4: Mar | G4: Apr | H4: May | I4: Jun | J4: Jul | K4: Aug | L4: Sep | M4: Oct | N4: Nov | O4: Dec | P4: Grand Total | T4: Row Labels | U4: Count of COUNTRY | V4: Sum of SALES | W4: Sum of % PROFIT | Y4: PRODUCTLINE | Z4: % PROFIT | AA4: DEALSIZE | AB4: SUM OF SALES | AC4: SUM OF PROFIT | BC4: Australia | BD4: Disputed
B5: Australia | C5: Classic Cars | D5: 3832 | F5: 4151.86 | H5: 23425.66 | J5: 25590.29 | L5: 52552.48 | N5: 83533.25 | P5: 193085.54 | T5: Classic Cars | U5: 949 | V5: 3842868.5 | W5: -1640.1546 | Y5: Motorcycles | Z5: =SUMIFS(Auto[% PROFIT], Auto[COUNTRY], $Z$1, Auto[PRODUCTLINE], Y5, Auto[STATUS], $Z$2) -> 0 | AA5: Small | AB5: =SUMIFS(Auto[SALES], Auto[COUNTRY], $Z$1, Auto[PRODUCTLINE], Y5) -> 0 | AC5: =SUMIFS(Auto[PROFIT], Auto[COUNTRY], $Z$1, Auto[PRODUCTLINE], Y5) -> 0 | BC5: Finland | BD5: In Process
B6: Australia | C6: Motorcycles | E6: 43380.46 | G6: 23475.59 | N6: 20331.81 | O6: 2780.9 | P6: 89968.76 | T6: Vintage Cars | U6: 579 | V6: 1806675.7 | W6: 792.7368 | Y6: Classic Cars | Z6: =SUMIFS(Auto[% PROFIT], Auto[COUNTRY], $Z$1, Auto[PRODUCTLINE], Y6, Auto[STATUS], $Z$2) -> 0 | AA6: Medium | AB6: =SUMIFS(Auto[SALES], Auto[COUNTRY], $Z$1, Auto[PRODUCTLINE], Y6) -> 157182.48 | AC6: =SUMIFS(Auto[PROFIT], Auto[COUNTRY], $Z$1, Auto[PRODUCTLINE], Y6) -> 459.48 | BC6: Austria | BD6: Cancelled
B7: Australia | C7: Planes | E7: 24769.68 | G7: 22347.02 | H7: 3843.84 | O7: 23893.33 | P7: 74853.87 | T7: Trucks and Buses | U7: 295 | V7: 1111559.2 | W7: 215.2319 | Y7: Trucks and Buses | Z7: =SUMIFS(Auto[% PROFIT], Auto[COUNTRY], $Z$1, Auto[PRODUCTLINE], Y7, Auto[STATUS], $Z$2) -> 0 | AA7: Large | AB7: =SUMIFS(Auto[SALES], Auto[COUNTRY], $Z$1, Auto[PRODUCTLINE], Y7) -> 9588.82 | AC7: =SUMIFS(Auto[PROFIT], Auto[COUNTRY], $Z$1, Auto[PRODUCTLINE], Y7) -> 1058.82 | BC7: UK | BD7: On Hold
B8: Australia | C8: Ships | H8: 3070.4 | O8: 1089.36 | P8: 4159.76 | T8: Motorcycles | U8: 313 | V8: 1103512.2 | W8: 263.7819 | Y8: Vintage Cars | Z8: =SUMIFS(Auto[% PROFIT], Auto[COUNTRY], $Z$1, Auto[PRODUCTLINE], Y8, Auto[STATUS], $Z$2) -> 0 | AB8: =SUMIFS(Auto[SALES], Auto[COUNTRY], $Z$1, Auto[PRODUCTLINE], Y8) -> 21105.81 | AC8: =SUMIFS(Auto[PROFIT], Auto[COUNTRY], $Z$1, Auto[PRODUCTLINE], Y8) -> -1200.19 | BC8: Spain | BD8: Resolved
B9: Australia | C9: Trains | L9: 1681.35 | P9: 1681.35 | T9: Planes | U9: 304 | V9: 969323.42 | W9: 225.2442 | Y9: Planes | Z9: =SUMIFS(Auto[% PROFIT], Auto[COUNTRY], $Z$1, Auto[PRODUCTLINE], Y9, Auto[STATUS], $Z$2) -> -1.1855 | AB9: =SUMIFS(Auto[SALES], Auto[COUNTRY], $Z$1, Auto[PRODUCTLINE], Y9) -> 7586.45 | AC9: =SUMIFS(Auto[PROFIT], Auto[COUNTRY], $Z$1, Auto[PRODUCTLINE], Y9) -> -118.55 | BC9: Sweden
B10: Australia | C10: Trucks and Buses | D10: 23290.17 | F10: 6626.7 | J10: 17715.31 | N10: 29686.32 | P10: 77318.5 | T10: Ships | U10: 230 | V10: 700039.22 | W10: 137.4322 | Y10: Ships | Z10: =SUMIFS(Auto[% PROFIT], Auto[COUNTRY], $Z$1, Auto[PRODUCTLINE], Y10, Auto[STATUS], $Z$2) -> 11.4916 | AB10: =SUMIFS(Auto[SALES], Auto[COUNTRY], $Z$1, Auto[PRODUCTLINE], Y10) -> 38697.26 | AC10: =SUMIFS(Auto[PROFIT], Auto[COUNTRY], $Z$1, Auto[PRODUCTLINE], Y10) -> 1270.26 | BC10: Singapore
B11: Australia | C11: Vintage Cars | D11: 2730 | E11: 3217.46 | F11: 24381.69 | G11: 4575.05 | H11: 37747.8 | J11: 38723.62 | L11: 3598.22 | N11: 64439.92 | O11: 10141.56 | P11: 189555.32 | T11: Trains | U11: 77 | V11: 226243.47 | W11: 291.9947 | Y11: Trains | Z11: =SUMIFS(Auto[% PROFIT], Auto[COUNTRY], $Z$1, Auto[PRODUCTLINE], Y11, Auto[STATUS], $Z$2) -> 0 | AB11: =SUMIFS(Auto[SALES], Auto[COUNTRY], $Z$1, Auto[PRODUCTLINE], Y11) -> 11476.33 | AC11: =SUMIFS(Auto[PROFIT], Auto[COUNTRY], $Z$1, Auto[PRODUCTLINE], Y11) -> 1002.33 | BC11: Canada
B12: Austria | C12: Classic Cars | G12: 5004.8 | H12: 59475.1 | M12: 6732.09 | N12: 30247.48 | P12: 101459.47 | T12: Grand Total | U12: 2747 | V12: 9760221.7 | W12: 286.2671 | BC12: Japan
B13: Austria | C13: Motorcycles | N13: 26047.66 | P13: 26047.66 | BC13: Italy
B14: Austria | C14: Planes | G14: 14216.32 | N14: 3644.12 | P14: 17860.44 | BC14: Denmark
B15: Austria | C15: Ships | G15: 9024.73 | P15: 9024.73 | BC15: Belgium
B16: Austria | C16: Trucks and Buses | M16: 20472.75 | P16: 20472.75 | BC16: Philippines
B17: Austria | C17: Vintage Cars | F17: 8775.16 | G17: 10383.29 | J17: 6693.28 | M17: 1345.75 | P17: 27197.48 | T17: COUNTRY | U17: SALES | Y17: PRODUCTLINE | Z17: TOTAL REVENUE | BC17: Germany
B18: Belgium | C18: Classic Cars | D18: 16628.16 | J18: 3508.8 | P18: 20136.96 | T18: USA | U18: =SUMIF('Auto Sales data'!R:R, T18,'Auto Sales data'!E:E) -> 3355575.7 | Y18: Classic Cars | Z18: =SUMIF('Auto Sales data'!J:J, Y18,'Auto Sales data'!E:E) -> 3842868.5 | BC18: Switzerland
B19: Belgium | C19: Planes | N19: 5624.79 | P19: 5624.79 | T19: Spain | U19: =SUMIF('Auto Sales data'!R:R, T19,'Auto Sales data'!E:E) -> 1215686.9 | Y19: Vintage Cars | Z19: =SUMIF('Auto Sales data'!J:J, Y19,'Auto Sales data'!E:E) -> 1806675.7 | BC19: Ireland
B20: Belgium | C20: Ships | E20: 9035.63 | J20: 20360.14 | N20: 2312.24 | P20: 31708.01 | T20: France | U20: =SUMIF('Auto Sales data'!R:R, T20,'Auto Sales data'!E:E) -> 1110916.5 | Y20: Trucks and Buses | Z20: =SUMIF('Auto Sales data'!J:J, Y20,'Auto Sales data'!E:E) -> 1111559.2
B21: Belgium | C21: Trains | E21: 1855.41 | G21: 1711.26 | J21: 5450.59 | P21: 9017.26 | T21: Australia | U21: =SUMIF('Auto Sales data'!R:R, T21,'Auto Sales data'!E:E) -> 630623.1 | Y21: Motorcycles | Z21: =SUMIF('Auto Sales data'!J:J, Y21,'Auto Sales data'!E:E) -> 1103512.2
B22: Belgium | C22: Vintage Cars | E22: 7909.05 | H22: 8411.95 | J22: 18440.95 | K22: 1637.2 | N22: 5526.45 | P22: 41925.6 | T22: UK | U22: =SUMIF('Auto Sales data'!R:R, T22,'Auto Sales data'!E:E) -> 478880.46 | Y22: Planes | Z22: =SUMIF('Auto Sales data'!J:J, Y22,'Auto Sales data'!E:E) -> 969323.42
B23: Canada | C23: Classic Cars | H23: 12144.76 | I23: 3378.24 | K23: 2992 | M23: 14224.15 | N23: 15947.29 | O23: 12936.78 | P23: 61623.22 | T23: Italy | U23: =SUMIF('Auto Sales data'!R:R, T23,'Auto Sales data'!E:E) -> 374674.31 | Y23: Ships | Z23: =SUMIF('Auto Sales data'!J:J, Y23,'Auto Sales data'!E:E) -> 700039.22
B24: Canada | C24: Motorcycles | G24: 4177.49 | P24: 4177.49 | T24: Finland | U24: =SUMIF('Auto Sales data'!R:R, T24,'Auto Sales data'!E:E) -> 329581.91 | Y24: Trains | Z24: =SUMIF('Auto Sales data'!J:J, Y24,'Auto Sales data'!E:E) -> 226243.47
B25: Canada | C25: Planes | G25: 23032.84 | K25: 2477.23 | P25: 25510.07 | T25: Norway | U25: =SUMIF('Auto Sales data'!R:R, T25,'Auto Sales data'!E:E) -> 307463.7
B26: Canada | C26: Ships | I26: 17389.95 | K26: 22919.06 | P26: 40309.01 | T26: Singapore | U26: =SUMIF('Auto Sales data'!R:R, T26,'Auto Sales data'!E:E) -> 288488.41
B27: Canada | C27: Trucks and Buses | H27: 19452.76 | M27: 22352.56 | O27: 10140.66 | P27: 51945.98 | T27: Denmark | U27: =SUMIF('Auto Sales data'!R:R, T27,'Auto Sales data'!E:E) -> 245637.15
B28: Canada | C28: Vintage Cars | G28: 4092.17 | H28: 2095.45 | I28: 3796.34 | K28: 14944.06 | O28: 15584.77 | P28: 40512.79 | T28: Canada | U28: =SUMIF('Auto Sales data'!R:R, T28,'Auto Sales data'!E:E) -> 224078.56
B29: Denmark | C29: Classic Cars | E29: 20464.41 | G29: 57342.43 | M29: 79375.64 | P29: 157182.48 | T29: Germany | U29: =SUMIF('Auto Sales data'!R:R, T29,'Auto Sales data'!E:E) -> 220472.09
B30: Denmark | C30: Planes | N30: 7586.45 | P30: 7586.45 | T30: Sweden | U30: =SUMIF('Auto Sales data'!R:R, T30,'Auto Sales data'!E:E) -> 210014.21
B31: Denmark | C31: Ships | E31: 20452.04 | M31: 1753.06 | N31: 16492.16 | P31: 38697.26 | T31: Austria | U31: =SUMIF('Auto Sales data'!R:R, T31,'Auto Sales data'!E:E) -> 202062.53
B32: Denmark | C32: Trains | E32: 4330.1 | M32: 7146.23 | P32: 11476.33 | T32: Japan | U32: =SUMIF('Auto Sales data'!R:R, T32,'Auto Sales data'!E:E) -> 188167.81
B33: Denmark | C33: Trucks and Buses | M33: 9588.82 | P33: 9588.82 | T33: Switzerland | U33: =SUMIF('Auto Sales data'!R:R, T33,'Auto Sales data'!E:E) -> 117713.56
B34: Denmark | C34: Vintage Cars | E34: 13624.56 | I34: 4749.45 | M34: 2731.8 | P34: 21105.81 | T34: Belgium | U34: =SUMIF('Auto Sales data'!R:R, T34,'Auto Sales data'!E:E) -> 108412.62
B35: Finland | C35: Classic Cars | D35: 39762.89 | E35: 26422.82 | G35: 17813.4 | H35: 25901.18 | K35: 16537.46 | L35: 22588.41 | M35: 4526.08 | P35: 153552.24 | T35: Philippines | U35: =SUMIF('Auto Sales data'!R:R, T35,'Auto Sales data'!E:E) -> 94015.73
B36: Finland | C36: Motorcycles | D36: 15656.85 | L36: 32209.87 | P36: 47866.72 | T36: Ireland | U36: =SUMIF('Auto Sales data'!R:R, T36,'Auto Sales data'!E:E) -> 57756.43
B37: Finland | C37: Planes | D37: 11262.27 | M37: 23112.86 | P37: 34375.13
B38: Finland | C38: Ships | D38: 23400.52 | M38: 6407.92 | P38: 29808.44
B39: Finland | C39: Trains | H39: 5117.05 | P39: 5117.05
B40: Finland | C40: Trucks and Buses | K40: 15031.97 | L40: 25447.36 | P40: 40479.33
B41: Finland | C41: Vintage Cars | D41: 10346.36 | M41: 8036.64 | P41: 18383
B42: France | C42: Classic Cars | D42: 41477.96 | E42: 3420 | F42: 19455.4 | G42: 79233.19 | H42: 99683.27 | J42: 32397.4 | M42: 14380.7 | N42: 79925.28 | O42: 18978 | P42: 388951.2
B43: France | C43: Motorcycles | D43: 26871.81 | E43: 45729.42 | G43: 14066.8 | H43: 34873.72 | J43: 48398.88 | K43: 2173.6 | L43: 5307.98 | N43: 45030.4 | O43: 3937.7 | P43: 226390.31
B44: France | C44: Planes | E44: 23802.47 | F44: 35567.48 | J44: 29712.92 | N44: 19072.64 | P44: 108155.51
B45: France | C45: Ships | D45: 23734.2 | F45: 21072.72 | M45: 15035.99 | N45: 6643.76 | P45: 66486.67
B46: France | C46: Trains | D46: 7582.86 | F46: 8977.05 | N46: 4856.42 | O46: 5924.47 | P46: 27340.8
B47: France | C47: Trucks and Buses | E47: 5759.42 | F47: 5692.96 | G47: 20223.07 | H47: 25173.01 | M47: 13533.44 | N47: 35344.94 | O47: 11255.38 | P47: 116982.22
B48: France | C48: Vintage Cars | D48: 8360.13 | E48: 6843.64 | F48: 43526.38 | G48: 13782.73 | I48: 5416.9 | J48: 3515.98 | M48: 36844.68 | N48: 35576.57 | O48: 22742.8 | P48: 176609.81
B49: Germany | C49: Classic Cars | F49: 28248.13 | M49: 91831.51 | N49: 28235.36 | P49: 148315
B50: Germany | C50: Motorcycles | M50: 4369.68 | N50: 3127.82 | P50: 7497.5
B51: Germany | C51: Planes | L51: 23001.26 | P51: 23001.26
B52: Germany | C52: Ships | L52: 5501 | P52: 5501
B53: Germany | C53: Trains | F53: 5043.42 | P53: 5043.42
B54: Germany | C54: Trucks and Buses | F54: 3974.94 | N54: 6203.06 | P54: 10178
B55: Germany | C55: Vintage Cars | D55: 11432.34 | L55: 6491.66 | N55: 3011.91 | P55: 20935.91
B56: Ireland | C56: Classic Cars | E56: 31688.82 | P56: 31688.82
B57: Ireland | C57: Motorcycles | L57: 4953.2 | P57: 4953.2
B58: Ireland | C58: Planes | L58: 11784.36 | P58: 11784.36
B59: Ireland | C59: Trains | E59: 3112.6 | P59: 3112.6
B60: Ireland | C60: Trucks and Buses | E60: 3983.05 | P60: 3983.05
B61: Ireland | C61: Vintage Cars | L61: 2234.4 | P61: 2234.4
B62: Italy | C62: Classic Cars | J62: 56421.65 | K62: 8014.82 | L62: 20906.8 | N62: 43233.38 | P62: 128576.65
B63: Italy | C63: Motorcycles | H63: 7567.8 | P63: 7567.8
B64: Italy | C64: Planes | E64: 39205.31 | H64: 30429.01 | N64: 28551.33 | P64: 98185.65
B65: Italy | C65: Ships | E65: 6598.34 | L65: 6948.62 | N65: 4156.58 | P65: 17703.54
B66: Italy | C66: Trains | L66: 2418.24 | N66: 3856.72 | P66: 6274.96
B67: Italy | C67: Trucks and Buses | K67: 2800.08 | N67: 3114.89 | P67: 5914.97
B68: Italy | C68: Vintage Cars | E68: 10377.67 | H68: 3513.13 | K68: 45263.36 | L68: 7765.34 | N68: 43531.24 | P68: 110450.74
B69: Japan | C69: Classic Cars | D69: 18835.02 | G69: 17114.43 | I69: 11322.04 | P69: 47271.49
B70: Japan | C70: Motorcycles | D70: 16646.15 | N70: 9890.26 | P70: 26536.41
B71: Japan | C71: Planes | D71: 29773.39 | N71: 19403.57 | P71: 49176.96
B72: Japan | C72: Ships | D72: 8407.33 | N72: 10452.69 | P72: 18860.02
B73: Japan | C73: Trains | D73: 3523.67 | P73: 3523.67
B74: Japan | C74: Trucks and Buses | I74: 13349.44 | P74: 13349.44
B75: Japan | C75: Vintage Cars | D75: 11496.47 | G75: 553.95 | I75: 1257.27 | N75: 16142.13 | P75: 29449.82
B76: Norway | C76: Classic Cars | D76: 15263.7 | M76: 45078.76 | N76: 74444.91 | P76: 134787.37
B77: Norway | C77: Motorcycles | M77: 21244.34 | N77: 30524.29 | P77: 51768.63
B78: Norway | C78: Planes | K78: 25543.65 | N78: 3957.05 | P78: 29500.7
B79: Norway | C79: Trains | N79: 11310.36 | P79: 11310.36
B80: Norway | C80: Trucks and Buses | D80: 23041.1 | N80: 14034.54 | P80: 37075.64
B81: Norway | C81: Vintage Cars | D81: 16397.2 | K81: 8601.82 | L81: 16363.1 | N81: 1658.88 | P81: 43021
B82: Philippines | C82: Classic Cars | F82: 42605.87 | N82: 10506.22 | P82: 53112.09
B83: Philippines | C83: Motorcycles | F83: 12639.15 | N83: 5422.53 | P83: 18061.68
B84: Philippines | C84: Planes | N84: 20906.87 | P84: 20906.87
B85: Philippines | C85: Vintage Cars | N85: 1935.09 | P85: 1935.09
B86: Singapore | C86: Classic Cars | E86: 9748.48 | G86: 20664.74 | I86: 15730.37 | K86: 3127.88 | L86: 42482.38 | M86: 41136.59 | P86: 132890.44
B87: Singapore | C87: Motorcycles | F87: 4175.6 | P87: 4175.6
B88: Singapore | C88: Ships | G88: 14155.52 | P88: 14155.52
B89: Singapore | C89: Trains | G89: 3045.21 | M89: 10233.5 | P89: 13278.71
B90: Singapore | C90: Trucks and Buses | E90: 14471.11 | I90: 30058.35 | L90: 18058.94 | M90: 26439.28 | P90: 89027.68
B91: Singapore | C91: Vintage Cars | G91: 8379.58 | L91: 26580.88 | P91: 34960.46
B92: Spain | C92: Classic Cars | D92: 91093.25 | E92: 77783.56 | F92: 33616.44 | H92: 80112.86 | K92: 21986.27 | L92: 17334.53 | M92: 31513.82 | N92: 36076.21 | O92: 86648.21 | P92: 476165.15
B93: Spain | C93: Motorcycles | E93: 7908.04 | H93: 31821.9 | I93: 2642.01 | N93: 21868.31 | O93: 10394.56 | P93: 74634.82
B94: Spain | C94: Planes | F94: 26946.47 | I94: 41905.81 | M94: 4954.08 | N94: 16179.15 | P94: 89985.51
B95: Spain | C95: Ships | F95: 23371.55 | G95: 4219.2 | I95: 9943.76 | L95: 20564.19 | N95: 45723.36 | O95: 20637.91 | P95: 124459.97
B96: Spain | C96: Trains | D96: 4933.55 | E96: 7209.84 | F96: 1808.4 | I96: 4837.18 | L96: 4353.17 | N96: 5516.12 | O96: 14711.92 | P96: 43370.18
B97: Spain | C97: Trucks and Buses | D97: 13760.33 | E97: 8632.8 | F97: 2259.72 | H97: 87706.08 | N97: 43779.04 | O97: 21418.81 | P97: 177556.78
B98: Spain | C98: Vintage Cars | D98: 24995.47 | E98: 29851.37 | F98: 3497.7 | G98: 28327.64 | H98: 21993.1 | I98: 30297.71 | L98: 5475.93 | M98: 7399.59 | N98: 36397.72 | O98: 41278.28 | P98: 229514.51
B99: Sweden | C99: Classic Cars | F99: 23248.58 | L99: 14249.05 | M99: 5924.16 | N99: 25666.27 | P99: 69088.06
B100: Sweden | C100: Motorcycles | F100: 15567.25 | P100: 15567.25
...

Sheet Sheet2
B1: PRODUCTLINE | C1: CUSTOMERNAME | D1: STATUS | E1: DEALSIZE | F1: COUNTRY
B2: Motorcycles | C2: Land of Toys Inc. | D2: Shipped | E2: Small | F2: USA
B3: Classic Cars | C3: Reims Collectables | D3: Disputed | E3: Medium | F3: France
B4: Trucks and Buses | C4: Lyon Souveniers | D4: In Process | E4: Large | F4: Norway
B5: Vintage Cars | C5: Toys4GrownUps.com | D5: Cancelled | F5: Australia
B6: Planes | C6: Technics Stores Inc. | D6: On Hold | F6: Finland
B7: Ships | C7: Daedalus Designs Imports | D7: Resolved | F7: Austria
B8: Trains | C8: Herkku Gifts | F8: UK
C9: Auto Canal Petit | F9: Spain
C10: Australian Collectors, Co. | F10: Sweden
C11: Vitachrome Inc. | F11: Singapore
C12: Tekni Collectables Inc. | F12: Canada
C13: Gift Depot Inc. | F13: Japan
C14: La Rochelle Gifts | E14: DEALSIZE | F14: Italy
C15: Marta's Replicas Co. | E15: Small | F15: Denmark
C16: Toys of Finland, Co. | E16: Medium | F16: Belgium
C17: Baane Mini Imports | E17: Large | F17: Philippines
C18: Diecast Classics Inc. | F18: Germany
C19: Salzburg Collectables | F19: Switzerland
C20: Souveniers And Things Co. | F20: Ireland
C21: FunGiftIdeas.com
C22: UK Collectables, Ltd.
C23: Euro Shopping Channel
C24: Volvo Model Replicas, Co
C25: Corrida Auto Replicas, Ltd
C26: Dragon Souveniers, Ltd.
C27: Classic Legends Inc.
C28: Australian Gift Network, Co
C29: Classic Gift Ideas, Inc
C30: Saveley & Henriot, Co.
C31: Canadian Gift Exchange Network
C32: West Coast Collectables Co.
... C90: Auto-Moto Classics Inc.
